llm_lmstudio.py
llm_lmstudio-0.2.1.dist-info/licenses/LICENSE
llm_lmstudio-0.2.1.dist-info/METADATA
llm_lmstudio-0.2.1.dist-info/WHEEL
llm_lmstudio-0.2.1.dist-info/entry_points.txt
llm_lmstudio-0.2.1.dist-info/top_level.txt
llm_lmstudio-0.2.1.dist-info/RECORD
