Metadata-Version: 2.4
Name: llm-lmstudio
Version: 0.2.1
Summary: LLM plugin for models served by LMStudio (local LLM studio HTTP API)
Author: Agusti
Project-URL: Homepage, https://github.com/agustif/llm-lmstudio
Project-URL: Issues, https://github.com/agustif/llm-lmstudio/issues
Project-URL: CI, https://github.com/agustif/llm-lmstudio/actions
Project-URL: Changelog, https://github.com/agustif/llm-lmstudio/releases
Requires-Python: >=3.10
License-File: LICENSE
Requires-Dist: llm>=0.23
Requires-Dist: requests>=2.0
Requires-Dist: httpx>=0.20
Dynamic: license-file
